[
  { "rank": 1, "team_name": "Liverpool", "team_logo": "https://upload.wikimedia.org/wikipedia/en/thumb/0/0c/Liverpool_FC.svg/1200px-Liverpool_FC.svg.png", "played": 20, "won": 15, "draw": 4, "lost": 1, "goals_for": 48, "goals_against": 16, "goal_difference": 32, "points": 49 },
  { "rank": 2, "team_name": "Manchester City", "team_logo": "https://upload.wikimedia.org/wikipedia/en/thumb/e/eb/Manchester_City_FC_badge.svg/1200px-Manchester_City_FC_badge.svg.png", "played": 20, "won": 14, "draw": 4, "lost": 2, "goals_for": 50, "goals_against": 19, "goal_difference": 31, "points": 46 },
  { "rank": 3, "team_name": "Arsenal", "team_logo": "https://upload.wikimedia.org/wikipedia/en/thumb/5/53/Arsenal_FC.svg/1200px-Arsenal_FC.svg.png", "played": 20, "won": 13, "draw": 5, "lost": 2, "goals_for": 42, "goals_against": 17, "goal_difference": 25, "points": 44 },
  { "rank": 4, "team_name": "Chelsea", "team_logo": "https://upload.wikimedia.org/wikipedia/en/thumb/c/cc/Chelsea_FC.svg/1200px-Chelsea_FC.svg.png", "played": 20, "won": 11, "draw": 6, "lost": 3, "goals_for": 38, "goals_against": 22, "goal_difference": 16, "points": 39 },
  { "rank": 5, "team_name": "Nottingham Forest", "team_logo": "https://upload.wikimedia.org/wikipedia/en/thumb/e/e5/Nottingham_Forest_F.C._logo.svg/1200px-Nottingham_Forest_F.C._logo.svg.png", "played": 20, "won": 10, "draw": 5, "lost": 5, "goals_for": 29, "goals_against": 21, "goal_difference": 8, "points": 35 },
  { "rank": 6, "team_name": "Aston Villa", "team_logo": "https://upload.wikimedia.org/wikipedia/en/thumb/f/f9/Aston_Villa_FC_crest_%282016%29.svg/1200px-Aston_Villa_FC_crest_%282016%29.svg.png", "played": 20, "won": 10, "draw": 4, "lost": 6, "goals_for": 33, "goals_against": 28, "goal_difference": 5, "points": 34 },
  { "rank": 7, "rank": 7, "team_name": "Tottenham", "team_logo": "https://upload.wikimedia.org/wikipedia/en/thumb/b/b4/Tottenham_Hotspur.svg/1200px-Tottenham_Hotspur.svg.png", "played": 20, "won": 10, "draw": 3, "lost": 7, "goals_for": 36, "goals_against": 29, "goal_difference": 7, "points": 33 },
  { "rank": 8, "team_name": "Newcastle United", "team_logo": "https://upload.wikimedia.org/wikipedia/en/thumb/5/56/Newcastle_United_Logo.svg/1200px-Newcastle_United_Logo.svg.png", "played": 20, "won": 9, "draw": 5, "lost": 6, "goals_for": 31, "goals_against": 27, "goal_difference": 4, "points": 32 },
  { "rank": 9, "team_name": "Brighton", "team_logo": "https://upload.wikimedia.org/wikipedia/en/thumb/f/f9/Brighton_and_Hove_Albion_FC_crest.svg/1200px-Brighton_and_Hove_Albion_FC_crest.svg.png", "played": 20, "won": 8, "draw": 7, "lost": 5, "goals_for": 32, "goals_against": 30, "goal_difference": 2, "points": 31 },
  { "rank": 10, "team_name": "Fulham", "team_logo": "https://upload.wikimedia.org/wikipedia/en/thumb/e/eb/Fulham_FC_%28shield%29.svg/1200px-Fulham_FC_%28shield%29.svg.png", "played": 20, "won": 8, "draw": 6, "lost": 6, "goals_for": 28, "goals_against": 26, "goal_difference": 2, "points": 30 },
  { "rank": 11, "team_name": "Bournemouth", "team_logo": "https://upload.wikimedia.org/wikipedia/en/thumb/e/e5/AFC_Bournemouth_%282013%29.svg/1200px-AFC_Bournemouth_%282013%29.svg.png", "played": 20, "won": 8, "draw": 4, "lost": 8, "goals_for": 27, "goals_against": 29, "goal_difference": -2, "points": 28 },
  { "rank": 12, "team_name": "Brentford", "team_logo": "https://upload.wikimedia.org/wikipedia/en/thumb/2/2a/Brentford_FC_crest.svg/1200px-Brentford_FC_crest.svg.png", "played": 20, "won": 8, "draw": 3, "lost": 9, "goals_for": 30, "goals_against": 32, "goal_difference": -2, "points": 27 },
  { "rank": 13, "team_name": "Manchester United", "team_logo": "https://upload.wikimedia.org/wikipedia/en/thumb/7/7a/Manchester_United_FC_crest.svg/1200px-Manchester_United_FC_crest.svg.png", "played": 20, "won": 7, "draw": 4, "lost": 9, "goals_for": 26, "goals_against": 28, "goal_difference": -2, "points": 25 },
  { "rank": 14, "team_name": "West Ham", "team_logo": "https://upload.wikimedia.org/wikipedia/en/thumb/c/c2/West_Ham_United_FC_logo.svg/1200px-West_Ham_United_FC_logo.svg.png", "played": 20, "won": 6, "draw": 5, "lost": 9, "goals_for": 24, "goals_against": 31, "goal_difference": -7, "points": 23 },
  { "rank": 15, "team_name": "Leicester City", "team_logo": "https://upload.wikimedia.org/wikipedia/en/thumb/2/2d/Leicester_City_crest.svg/1200px-Leicester_City_crest.svg.png", "played": 20, "won": 5, "draw": 5, "lost": 10, "goals_for": 22, "goals_against": 35, "goal_difference": -13, "points": 20 },
  { "rank": 16, "team_name": "Everton", "team_logo": "https://upload.wikimedia.org/wikipedia/en/thumb/7/7c/Everton_FC_logo.svg/1200px-Everton_FC_logo.svg.png", "played": 20, "won": 4, "draw": 6, "lost": 10, "goals_for": 19, "goals_against": 30, "goal_difference": -11, "points": 18 },
  { "rank": 17, "team_name": "Crystal Palace", "team_logo": "https://upload.wikimedia.org/wikipedia/en/thumb/a/a2/Crystal_Palace_FC_logo_%282022%29.svg/1200px-Crystal_Palace_FC_logo_%282022%29.svg.png", "played": 20, "won": 3, "draw": 7, "lost": 10, "goals_for": 18, "goals_against": 32, "goal_difference": -14, "points": 16 },
  { "rank": 18, "team_name": "Ipswich Town", "team_logo": "https://upload.wikimedia.org/wikipedia/en/thumb/4/43/Ipswich_Town.svg/1200px-Ipswich_Town.svg.png", "played": 20, "won": 3, "draw": 6, "lost": 11, "goals_for": 17, "goals_against": 38, "goal_difference": -21, "points": 15 },
  { "rank": 19, "team_name": "Wolverhampton", "team_logo": "https://upload.wikimedia.org/wikipedia/en/thumb/f/fc/Wolverhampton_Wanderers.svg/1200px-Wolverhampton_Wanderers.svg.png", "played": 20, "won": 3, "draw": 5, "lost": 12, "goals_for": 20, "goals_against": 42, "goal_difference": -22, "points": 14 },
  { "rank": 20, "team_name": "Southampton", "team_logo": "https://upload.wikimedia.org/wikipedia/en/thumb/c/c9/Southampton_FC.svg/1200px-Southampton_FC.svg.png", "played": 20, "won": 2, "draw": 4, "lost": 14, "goals_for": 15, "goals_against": 45, "goal_difference": -30, "points": 10 }
]
